{
  "alps" : {
    "version" : "1.0",
    "doc" : {
      "href" : "http://en.wikipedia.org/wiki/Generalized_linear_model"
    },
    "descriptor" : [
      {
        "id" : "generalizedLinearModel",
        "type" : "semantic",
        "description" : {"value" : "Generalized Linear Model fit"},
        "semantic" : [
          {
	    "id" : "formula",
            "type" : "semantic",
            "description" : {"value" : "Formula of the generalized linear model"},
            "href" : "http://alps.io/schema.org/Text"
          },
	  {
	    "id" : "family",
            "type" : "semantic",
            "description" : {"value" : "Error family of the generalized linear model"},
            "href" : "http://alps.io/schema.org/Text"
          },
	  {
	    "id" : "coefficient",
            "type" : "semantic",
            "description" : {"value" : "Generalized linear model coefficient"},
            "href" : "https://raw.github.com/standard-analytics/Schemas/master/coefficient.json"
          },
          {
	    "id" : "coefficients",
            "type" : "semantic",
            "description" : {"value" : "Generalized linear model coefficient  (legacy spelling; see singular form, coefficient)"},
	    "href" : "https://raw.github.com/standard-analytics/Schemas/master/coefficient.json"
          },
	  {
	    "id" : "R2",
            "type" : "semantic",
            "description" : {"value" : "R-squared"},
	    "href" : "http://alps.io/schema.org/Float"
          },
 	  {
	    "id" : "adjR2",
            "type" : "semantic",
            "description" : {"value" : "Adjusted r-squared"},
	    "href" : "http://alps.io/schema.org/Float"
          },
	  {
	    "id" : "FTest",
            "type" : "semantic",
            "description" : {"value" : "F test"},
            "href" : "https://raw.github.com/standard-analytics/Schemas/master/FTest.json"
          },
          {
	    "id" : "description",
            "type" : "semantic",
            "description" : {"value" : "Description of the hypothesis being tested."},
	    "href" : "http://schema.org/description"
	  }
        ]
      }
    ]
  }
}
